LICENSE
MANIFEST.in
README.rst
setup.py
django_gotuskra.egg-info/PKG-INFO
django_gotuskra.egg-info/SOURCES.txt
django_gotuskra.egg-info/dependency_links.txt
django_gotuskra.egg-info/not-zip-safe
django_gotuskra.egg-info/requires.txt
django_gotuskra.egg-info/top_level.txt
djgotuskra/__init__.py
djgotuskra/conf.py
djgotuskra/download.py
djgotuskra/models.py
djgotuskra/test.py
djgotuskra/management/__init__.py