Metadata-Version: 1.0
Name: django-gotuskra
Version: 0.1
Summary: UNKNOWN
Home-page: UNKNOWN
Author: Stefan Kjartansson
Author-email: esteban.supreme@gmail.com
License: UNKNOWN
Platform: UNKNOWN
Classifier: Development Status :: 4 - Beta
Classifier: Intended Audience :: Developers
Classifier: License :: OSI Approved :: MIT License
Classifier: Operating System :: OS Independent
Classifier: Programming Language :: Python
